sportran/README.md
sportran/__init__.py
sportran/analysis.py
sportran/metadata.json
sportran/current/__init__.py
sportran/current/current.py
sportran/current/electric.py
sportran/current/generic.py
sportran/current/heat.py
sportran/current/stress.py
sportran/current/tools/__init__.py
sportran/current/tools/fstar_analysis.py
sportran/current/units/__init__.py
sportran/current/units/constants.py
sportran/current/units/electric.py
sportran/current/units/heat.py
sportran/current/units/stress.py
sportran/i_o/__init__.py
sportran/i_o/read_lammps_datafile.py
sportran/i_o/read_lammps_dump.py
sportran/i_o/read_lammps_log.py
sportran/i_o/read_tablefile.py
sportran/md/__init__.py
sportran/md/aic.py
sportran/md/cepstral.py
sportran/md/mdsample.py
sportran/md/resample.py
sportran/md/tools/__init__.py
sportran/md/tools/acf.py
sportran/md/tools/armodel.py
sportran/md/tools/filter.py
sportran/md/tools/lpfilter.py
sportran/md/tools/resample.py
sportran/md/tools/spectrum.py
sportran/plotter/__init__.py
sportran/plotter/cli.py
sportran/plotter/current.py
sportran/plotter/mdsample.py
sportran/plotter/plotter.py
sportran/plotter/style.py
sportran/plotter/styles/__init__.py
sportran/plotter/styles/api_style.mplstyle
sportran/plotter/styles/cli_style.mplstyle
sportran/utils/__init__.py
sportran/utils/attributedict.py
sportran/utils/decorators.py
sportran/utils/logger.py
sportran_gui/README_GUI.md
sportran_gui/__init__.py
sportran_gui/main.py
sportran_gui/assets/__init__.py
sportran_gui/assets/icon.gif
sportran_gui/assets/languages.json
sportran_gui/core/__init__.py
sportran_gui/core/control_unit.py
sportran_gui/core/settings.py
sportran_gui/interfaces/__init__.py
sportran_gui/interfaces/fileManager.py
sportran_gui/interfaces/fstarSelector.py
sportran_gui/interfaces/headerSelector.py
sportran_gui/interfaces/otherVariables.py
sportran_gui/interfaces/pstarSelector.py
sportran_gui/utils/__init__.py
sportran_gui/utils/custom_widgets.py
sportran_gui/utils/utils.py
sportran-1.0.0rc4.dist-info/LICENSE.txt
sportran-1.0.0rc4.dist-info/METADATA
sportran-1.0.0rc4.dist-info/WHEEL
sportran-1.0.0rc4.dist-info/entry_points.txt
sportran-1.0.0rc4.dist-info/top_level.txt
sportran-1.0.0rc4.dist-info/RECORD
