Metadata-Version: 2.1
Name: sportran
Version: 1.0.0rc4
Summary: Cepstral Data Analysis of current time series for Green-Kubo transport coefficients
Home-page: https://github.com/sissaschool/sportran
Author: Loris Ercole, Riccardo Bertossa, Sebastiano Bisacchi
Author-email: loris.ercole@epfl.ch
License: GPL 3
Keywords: cepstral data analysis thermal conductivity transport coefficients physics green-kubo
Platform: UNKNOWN
Classifier: Development Status :: 5 - Production/Stable
Classifier: Programming Language :: Python
Classifier: Programming Language :: Python :: 3.7
Classifier: Programming Language :: Python :: 3.8
Classifier: Programming Language :: Python :: 3.9
Classifier: Programming Language :: Python :: 3.10
Classifier: Programming Language :: Python :: 3.11
Classifier: License :: OSI Approved :: GNU General Public License v3 (GPLv3)
Classifier: Operating System :: OS Independent
Classifier: Intended Audience :: Science/Research
Classifier: Intended Audience :: Developers
Classifier: Natural Language :: English
Classifier: Topic :: Scientific/Engineering :: Information Analysis
Classifier: Topic :: Scientific/Engineering :: Physics
Classifier: Environment :: Console
Requires-Python: >=3.7, <4
Requires-Dist: numpy (>=1.18.0)
Requires-Dist: scipy (>=1.3.2)
Requires-Dist: matplotlib (>=3.1.2)
Requires-Dist: markdown2 (>=2.0.0)
Requires-Dist: pillow (>=5.4.0)
Provides-Extra: doc
Requires-Dist: sphinx (==4.2.0) ; extra == 'doc'
Requires-Dist: myst-parser (==0.15.2) ; extra == 'doc'
Requires-Dist: nbsphinx (==0.8.7) ; extra == 'doc'
Provides-Extra: notebook
Requires-Dist: jupyter ; extra == 'notebook'
Provides-Extra: pre-commit
Requires-Dist: pre-commit (>=1.11.0) ; extra == 'pre-commit'
Requires-Dist: yapf (==0.32.0) ; extra == 'pre-commit'
Provides-Extra: tests
Requires-Dist: pytest (>=5.1.0) ; extra == 'tests'
Requires-Dist: pytest-regressions (>=2.4.2) ; extra == 'tests'
Requires-Dist: pandas (>=1.1.0) ; extra == 'tests'
Requires-Dist: testbook ; extra == 'tests'
Requires-Dist: ipykernel ; extra == 'tests'
